LICENSE.txt
README.md
setup.py
multisimil/__init__.py
multisimil/multisimil.py
multisimil.egg-info/PKG-INFO
multisimil.egg-info/SOURCES.txt
multisimil.egg-info/dependency_links.txt
multisimil.egg-info/requires.txt
multisimil.egg-info/top_level.txt