Metadata-Version: 2.1
Name: multisimil
Version: 0.0.1.1
Summary: A python package to find similarity between two images at multiple scales.
Home-page: https://github.com/pratik-tan10/multisimil
Author: Pratik Dhungana
Author-email: pdhungana@crimson.ua.edu
Keywords: python,multisimil,land use validation,categorical similarity,multi-scale similarity
Classifier: Development Status :: 5 - Production/Stable
Classifier: Intended Audience :: Education
Classifier: Operating System :: OS Independent
Classifier: License :: OSI Approved :: MIT License
Classifier: Programming Language :: Python :: 3
Classifier: Programming Language :: Python :: 3.5
Classifier: Programming Language :: Python :: 3.6
Classifier: Programming Language :: Python :: 3.7
Classifier: Programming Language :: Python :: 3.8
License-File: LICENSE.txt
